l2mac/__init__.py
l2mac/config.py
l2mac/core.py
l2mac/l2mac.py
l2mac/envs/__init__.py
l2mac/envs/general.py
l2mac/llm_providers/__init__.py
l2mac/llm_providers/general.py
l2mac/llm_providers/openai.py
l2mac/llm_providers/rate_limiter.py
l2mac/llm_providers/utils.py
l2mac/prompts/__init__.py
l2mac/prompts/book.yaml
l2mac/prompts/codebase.yaml
l2mac/prompts/custom.yaml
l2mac/prompts/load_prompts.py
l2mac/tools/__init__.py
l2mac/tools/code_analysis.py
l2mac/tools/control_unit.py
l2mac/tools/core.py
l2mac/tools/read.py
l2mac/tools/utils.py
l2mac/tools/write.py
l2mac/utils/__init__.py
l2mac/utils/l2mac.py
l2mac/utils/logging.py
l2mac/utils/run.py
l2mac-0.0.3.dist-info/LICENSE
l2mac-0.0.3.dist-info/METADATA
l2mac-0.0.3.dist-info/WHEEL
l2mac-0.0.3.dist-info/entry_points.txt
l2mac-0.0.3.dist-info/top_level.txt
l2mac-0.0.3.dist-info/RECORD
