Metadata-Version: 2.1
Name: l2mac
Version: 0.0.3
Summary: The LLM Automatic Computer Framework
Home-page: https://github.com/samholt/l2mac
Author: Sam Holt
Author-email: samuel.holt.direct@gmail.com
License: MIT
Keywords: l2mac multi-agent programming gpt llm metaprogramming automatic computer llm-automatic
Requires-Python: >=3.9
License-File: LICENSE
Requires-Dist: pyyaml
Requires-Dist: pydantic
Requires-Dist: typer>=0.9.0
Requires-Dist: numpy
Requires-Dist: openai
Requires-Dist: tiktoken
Requires-Dist: timeout-decorator
Requires-Dist: pygame==2.1.2
Provides-Extra: dev
Requires-Dist: pylint~=3.0.3; extra == "dev"
Requires-Dist: black~=23.3.0; extra == "dev"
Requires-Dist: isort~=5.12.0; extra == "dev"
Requires-Dist: pre-commit~=3.6.0; extra == "dev"
Requires-Dist: pytype~=2024.10.11; extra == "dev"
